foliant/cli/subset.py
foliantcontrib.subset-1.0.9.dist-info/LICENSE
foliantcontrib.subset-1.0.9.dist-info/METADATA
foliantcontrib.subset-1.0.9.dist-info/WHEEL
foliantcontrib.subset-1.0.9.dist-info/top_level.txt
foliantcontrib.subset-1.0.9.dist-info/RECORD
